<?xml version="1.0" encoding="UTF-8"?>
<item><pubDate>Fri, 21 May 2021 20:23:38 +0700</pubDate><title><![CDATA[Website Application]]></title><url><![CDATA[gallery]]></url><meta><![CDATA[]]></meta><metad><![CDATA[]]></metad><menu><![CDATA[Gallery]]></menu><menuOrder><![CDATA[0]]></menuOrder><menuStatus><![CDATA[]]></menuStatus><template><![CDATA[template.php]]></template><parent><![CDATA[]]></parent><content><![CDATA[&lt;div class=&quot;ratio ratio-21x9 rounded&quot;&gt;&lt;iframe allow=&quot;accelerometer; autoplay; clipboard-write; encrypted-media; gyroscope; picture-in-picture&quot; allowfullscreen=&quot;&quot; class=&quot;rounded shadow&quot; frameborder=&quot;0&quot; height=&quot;591&quot; src=&quot;https://www.youtube.com/embed/t7aApMXibck&quot; width=&quot;1379&quot;&gt;&lt;/iframe&gt;&lt;/div&gt;

&lt;div class=&quot;col-12 col-md-12 p-3 p-md-5&quot;&gt;
	&lt;h3&gt;&lt;strong&gt;&lt;a href=&quot;/&quot;&gt;Website Application &lt;/a&gt;&lt;/strong&gt;&lt;/h3&gt;

	&lt;p&gt;Dengan semakin berkembang dan maju nya technology kami sadar bahwasanya wajib lah kita untuk mengikuti perkembangan technology apps, agar menjadikan dan memulai yang terbaik untuk masa depan baik untuk pembukuan hingga kebutuhan untuk bertransaksi sekaligus promosi usaha via website online shop yang anda kelola secara penuh, untuk itulah team developer kami mengembangkan sebuah technology terbaik yang terintegrasi dengan aplikasi online clouds kasir penjualan toko dengan online shop toko online website hingga menyentuh dengan aplikasi android untuk kemudahan dan mobilitas dalam bekerja , dan kini dunia dalam genggaman anda dengan web app solutions ini.&lt;/p&gt;

	&lt;div class=&quot;ratio ratio-16x9 rounded&quot;&gt;&lt;iframe allow=&quot;accelerometer; autoplay; clipboard-write; encrypted-media; gyroscope; picture-in-picture&quot; allowfullscreen=&quot;&quot; class=&quot;rounded shadow&quot; frameborder=&quot;0&quot; height=&quot;591&quot; src=&quot;https://www.youtube.com/embed/Xp_sHwn15aQ&quot; width=&quot;1379&quot;&gt;&lt;/iframe&gt;&lt;/div&gt;

	&lt;p&gt;Pelajari aplikasi website ini bekerja dengan sentuhan kemudahan integrasi aplikasi dan website online shop toko mu menjadi satu smeakin mempercepat pekerjaan dengan technology ini dalam penerapan nya.&lt;/p&gt;

	&lt;div class=&quot;ratio ratio-16x9 rounded&quot;&gt;&lt;iframe allow=&quot;accelerometer; autoplay; clipboard-write; encrypted-media; gyroscope; picture-in-picture&quot; allowfullscreen=&quot;&quot; class=&quot;rounded shadow&quot; frameborder=&quot;0&quot; height=&quot;591&quot; src=&quot;https://www.youtube.com/embed/EM34fXx-Qe8&quot; width=&quot;1379&quot;&gt;&lt;/iframe&gt;&lt;/div&gt;

	&lt;p&gt;Setuh dengan android untuk kemudahan integrasi bekerja via smartphone android dengan cepat via web apps solutions kami untuk digunakan.&lt;/p&gt;

	&lt;p&gt;Saat nya update dan revolusi digital technology anda bersama kami untuk masa depan yang terbaik, Pilih web app mu dan &lt;a class=&quot;text-danger&quot; href=&quot;https://www.hockeycomputindo.com/p/toko.html&quot; target=&quot;_blank&quot;&gt;mulai sekarang disini →&lt;/a&gt;&lt;/p&gt;
&lt;/div&gt;
]]></content><private><![CDATA[]]></private><author><![CDATA[axcora]]></author></item>
